s3workers/__init__.py
s3workers/cli.py
s3workers/jobs.py
s3workers/manager.py
s3workers/progress.py
s3workers/reducer.py
s3workers/work_queue.py
s3workers/worker.py
s3workers-0.3.0.dist-info/DESCRIPTION.rst
s3workers-0.3.0.dist-info/METADATA
s3workers-0.3.0.dist-info/RECORD
s3workers-0.3.0.dist-info/WHEEL
s3workers-0.3.0.dist-info/entry_points.txt
s3workers-0.3.0.dist-info/metadata.json
s3workers-0.3.0.dist-info/top_level.txt
