Metadata-Version: 2.0
Name: s3workers
Version: 0.3.0
Summary: Helper to simplify concurrent access to object scanning in AWS S3 buckets.
Home-page: https://github.com/bradrf/s3workers
Author: Brad Robel-Forrest
Author-email: brad@bitpony.com
License: MIT license
Keywords: s3workers
Platform: UNKNOWN
Classifier: Development Status :: 2 - Pre-Alpha
Classifier: Intended Audience :: Developers
Classifier: License :: OSI Approved :: MIT License
Classifier: Natural Language :: English
Classifier: Programming Language :: Python :: 2
Classifier: Programming Language :: Python :: 2.6
Classifier: Programming Language :: Python :: 2.7
Classifier: Programming Language :: Python :: 3
Classifier: Programming Language :: Python :: 3.3
Classifier: Programming Language :: Python :: 3.4
Classifier: Programming Language :: Python :: 3.5
Requires-Dist: Click (>=6.6)
Requires-Dist: boto (>=2.45.0)
Requires-Dist: configstruct (>=0.3.0)
Requires-Dist: future (>=0.16.0)
